isawaartnet/__init__.py
isawaartnet/core.py
isawaartnet-1.0.0.dist-info/licenses/LICENSE
isawaartnet-1.0.0.dist-info/METADATA
isawaartnet-1.0.0.dist-info/WHEEL
isawaartnet-1.0.0.dist-info/top_level.txt
isawaartnet-1.0.0.dist-info/RECORD
