Metadata-Version: 2.4
Name: isawaartnet
Version: 1.0.0
Summary: DMX to Art-Net 4 Converter Library(But send only)
Author-email: inu <yukkiamp993@gmail.com>
License: MIT
Project-URL: Homepage, https://github.com/sen10/isawaArtnet
Project-URL: Documentation, https://github.com/sen10/isawaArtnet#readme
Project-URL: Repository, https://github.com/sen10/isawaArtnet
Project-URL: Issues, https://github.com/sen10/isawaArtnet/issues
Keywords: artnet,dmx,dmx512,lighting,stage
Classifier: Development Status :: 4 - Beta
Classifier: Intended Audience :: Developers
Classifier: License :: OSI Approved :: MIT License
Classifier: Programming Language :: Python :: 3
Classifier: Programming Language :: Python :: 3.8
Classifier: Programming Language :: Python :: 3.9
Classifier: Programming Language :: Python :: 3.10
Classifier: Programming Language :: Python :: 3.11
Classifier: Programming Language :: Python :: 3.12
Classifier: Topic :: System :: Networking
Classifier: Topic :: Multimedia
Requires-Python: >=3.8
License-File: LICENSE
Dynamic: license-file
